logpool/__init__.py
logpool/log.py
logpool-3.6.dist-info/licenses/LICENSE
logpool-3.6.dist-info/METADATA
logpool-3.6.dist-info/WHEEL
logpool-3.6.dist-info/top_level.txt
logpool-3.6.dist-info/RECORD
