Metadata-Version: 2.4
Name: logpool
Version: 3.6
Summary: Log and threading easy
Home-page: https://github.com/schwarzam/logpool
Author: Gustavo Schwarz
Author-email: gustavo.b.schwarz@gmail.com
Classifier: Programming Language :: Python :: 3
Classifier: License :: OSI Approved :: Apache Software License
License-File: LICENSE
Dynamic: author
Dynamic: author-email
Dynamic: classifier
Dynamic: home-page
Dynamic: license-file
Dynamic: summary
